{
  "uuid": "gnome-usb-mon@ska1006.github.io",
  "name": "USB & PD Monitor",
  "description": "Monitor connected USB devices and USB-C Power Delivery chargers: negotiated watts, PDO profiles, port roles and battery charge rate. Reads sysfs (typec, power_supply) via GUdev; no root required.",
  "shell-version": ["50"],
  "settings-schema": "org.gnome.shell.extensions.gnome-usb-mon",
  "gettext-domain": "gnome-usb-mon",
  "url": "https://github.com/Ska1006/gnomeUsbMon",
  "version": 1,
  "version-name": "1.0"
}
